cohortfinder/__init__.py
cohortfinder/__main__.py
cohortfinder/_version.py
cohortfinder/cohortfinder.py
cohortfinder-1.0.1.dist-info/METADATA
cohortfinder-1.0.1.dist-info/WHEEL
cohortfinder-1.0.1.dist-info/entry_points.txt
cohortfinder-1.0.1.dist-info/top_level.txt
cohortfinder-1.0.1.dist-info/RECORD
